{
  "schema": "ana-recruiting-pipeline-v1",
  "status": "active",
  "owner": "Ana / Recruiter",
  "authority": "Level 4 scoped autonomy only",
  "created_at": "2026-06-22T12:39:43-06:00",
  "updated_at": "2026-06-24T17:58:00-06:00",
  "source_backlog": "C:\\Users\\scott\\Code\\mindshare\\roles\\recruiter\\recruiting.backlog.md",
  "promotion_rules": {
    "backlog_to_level_1": "immediate when valid approved backlog item is processed",
    "level_1_to_level_2": "after 24 hours at Level 1",
    "level_2_to_level_3": "after five days at Level 2",
    "level_3_to_level_4": "not allowed by Ana Level 4"
  },
  "boundaries": [
    "no external recruiting",
    "no human candidate contact",
    "no Git/GitHub/release",
    "no production or website edits",
    "no spending",
    "no secrets",
    "no authority beyond Level 3 Staff",
    "no broad autonomous runtime"
  ],
  "items": [
    {
      "id": "REC-001",
      "org_chart_seat": "Chief Operating Officer",
      "role_title": "Operations Director",
      "organization": "Mindshare",
      "owner_route": "Rae / Chief Executive Officer",
      "priority": "High",
      "current_stage": "level_2_trainee",
      "stage_entered_at": "2026-06-24T16:54:30-06:00",
      "next_eligible_stage": "level_3_staff",
      "next_eligible_at": "2026-06-29T16:54:30-06:00",
      "status": "active",
      "level_1_packet": "C:\\Users\\scott\\Code\\mindshare\\roles\\recruiter\\level-4-work\\REC-001.md",
      "level_2_packet": "C:\\Users\\scott\\Code\\mindshare\\roles\\recruiter\\level-4-work\\REC-001-level2.md",
      "level_3_packet": null,
      "notes": "Named by Scott-directed Ana roster pass on 2026-06-24; remains an unactivated Level 2 Trainee packet. Seeded from completed Level 1 New Hire packet proof run; promotion timers governed by Ana Level 4 scoped autonomy.",
      "level_2_drive_packet": "G:\\My Drive\\Mindshare\\role\\recruiter\\level-4-work\\REC-001-level2.md",
      "person_name": "Morgan Vale",
      "display_name": "Morgan Vale / Operations Director"
    },
    {
      "id": "REC-002",
      "org_chart_seat": "Chief Product Officer",
      "role_title": "Product Director",
      "organization": "Mindshare",
      "owner_route": "Rae / Chief Executive Officer",
      "priority": "High",
      "current_stage": "level_2_trainee",
      "stage_entered_at": "2026-06-24T16:54:30-06:00",
      "next_eligible_stage": "level_3_staff",
      "next_eligible_at": "2026-06-29T16:54:30-06:00",
      "status": "active",
      "level_1_packet": "C:\\Users\\scott\\Code\\mindshare\\roles\\recruiter\\level-4-work\\REC-002.md",
      "level_2_packet": "C:\\Users\\scott\\Code\\mindshare\\roles\\recruiter\\level-4-work\\REC-002-level2.md",
      "level_3_packet": null,
      "notes": "Named by Scott-directed Ana roster pass on 2026-06-24; remains an unactivated Level 2 Trainee packet. Seeded from completed Level 1 New Hire packet proof run; promotion timers governed by Ana Level 4 scoped autonomy.",
      "level_2_drive_packet": "G:\\My Drive\\Mindshare\\role\\recruiter\\level-4-work\\REC-002-level2.md",
      "person_name": "Priya Sen",
      "display_name": "Priya Sen / Product Director"
    },
    {
      "id": "REC-003",
      "org_chart_seat": "Chief Technology Officer",
      "role_title": "Technology Director",
      "organization": "Mindshare",
      "owner_route": "Rae / Chief Executive Officer; coordinate with Vik",
      "priority": "High",
      "current_stage": "level_2_trainee",
      "stage_entered_at": "2026-06-24T16:54:30-06:00",
      "next_eligible_stage": "level_3_staff",
      "next_eligible_at": "2026-06-29T16:54:30-06:00",
      "status": "active",
      "level_1_packet": "C:\\Users\\scott\\Code\\mindshare\\roles\\recruiter\\level-4-work\\REC-003.md",
      "level_2_packet": "C:\\Users\\scott\\Code\\mindshare\\roles\\recruiter\\level-4-work\\REC-003-level2.md",
      "level_3_packet": null,
      "notes": "Named by Scott-directed Ana roster pass on 2026-06-24; remains an unactivated Level 2 Trainee packet. Seeded from completed Level 1 New Hire packet proof run; promotion timers governed by Ana Level 4 scoped autonomy.",
      "level_2_drive_packet": "G:\\My Drive\\Mindshare\\role\\recruiter\\level-4-work\\REC-003-level2.md",
      "person_name": "Owen Kline",
      "display_name": "Owen Kline / Technology Director"
    },
    {
      "id": "REC-004",
      "org_chart_seat": "Engineering",
      "role_title": "Engineering Director",
      "organization": "Mindshare / Mojo",
      "owner_route": "Technology Director once hired; interim Vik/Cal coordination",
      "priority": "High",
      "current_stage": "level_2_trainee",
      "stage_entered_at": "2026-06-24T16:54:30-06:00",
      "next_eligible_stage": "level_3_staff",
      "next_eligible_at": "2026-06-29T16:54:30-06:00",
      "status": "active",
      "level_1_packet": "C:\\Users\\scott\\Code\\mindshare\\roles\\recruiter\\level-4-work\\REC-004.md",
      "level_2_packet": "C:\\Users\\scott\\Code\\mindshare\\roles\\recruiter\\level-4-work\\REC-004-level2.md",
      "level_3_packet": null,
      "notes": "Named by Scott-directed Ana roster pass on 2026-06-24; remains an unactivated Level 2 Trainee packet. Seeded from completed Level 1 New Hire packet proof run; promotion timers governed by Ana Level 4 scoped autonomy.",
      "level_2_drive_packet": "G:\\My Drive\\Mindshare\\role\\recruiter\\level-4-work\\REC-004-level2.md",
      "person_name": "Nia Calder",
      "display_name": "Nia Calder / Engineering Director"
    },
    {
      "id": "REC-005",
      "org_chart_seat": "Platform Engineering",
      "role_title": "Platform Engineering Director",
      "organization": "Mojo",
      "owner_route": "Engineering Director once hired; interim Vik",
      "priority": "Medium",
      "current_stage": "level_2_trainee",
      "stage_entered_at": "2026-06-24T16:54:30-06:00",
      "next_eligible_stage": "level_3_staff",
      "next_eligible_at": "2026-06-29T16:54:30-06:00",
      "status": "active",
      "level_1_packet": "C:\\Users\\scott\\Code\\mindshare\\roles\\recruiter\\level-4-work\\REC-005.md",
      "level_2_packet": "C:\\Users\\scott\\Code\\mindshare\\roles\\recruiter\\level-4-work\\REC-005-level2.md",
      "level_3_packet": null,
      "notes": "Named by Scott-directed Ana roster pass on 2026-06-24; remains an unactivated Level 2 Trainee packet. Seeded from completed Level 1 New Hire packet proof run; promotion timers governed by Ana Level 4 scoped autonomy.",
      "level_2_drive_packet": "G:\\My Drive\\Mindshare\\role\\recruiter\\level-4-work\\REC-005-level2.md",
      "person_name": "Mateo Ruiz",
      "display_name": "Mateo Ruiz / Platform Engineering Director"
    },
    {
      "id": "REC-006",
      "org_chart_seat": "Data Engineering",
      "role_title": "Data Engineering Director",
      "organization": "Mojo",
      "owner_route": "Engineering Director once hired; interim Technology Director once hired",
      "priority": "Medium",
      "current_stage": "activated_operator",
      "stage_entered_at": "2026-06-24T17:58:00-06:00",
      "next_eligible_stage": null,
      "next_eligible_at": null,
      "status": "activated",
      "level_1_packet": "C:\\Users\\scott\\Code\\mindshare\\roles\\recruiter\\level-4-work\\REC-006.md",
      "level_2_packet": "C:\\Users\\scott\\Code\\mindshare\\roles\\recruiter\\level-4-work\\REC-006-level2.md",
      "level_3_packet": null,
      "notes": "Activated by Scott as Imani / Data Engineering Director on 2026-06-24. Removed from timed Level 2/3 packet promotion queue; future changes require role-owner approval and data/engineering authority gates.",
      "level_2_drive_packet": "G:\\My Drive\\Mindshare\\role\\recruiter\\level-4-work\\REC-006-level2.md",
      "person_name": "Imani",
      "display_name": "Imani / Data Engineering Director",
      "activated_role": "Imani",
      "activated_at": "2026-06-24T17:58:00-06:00",
      "activated_thread_id": "019efc1d-b79a-7dd2-9a62-a7ff4e901cde",
      "activated_role_path": "C:\\Users\\scott\\Code\\mojo\\roles\\data-engineering-director\\role-agent.md"
    },
    {
      "id": "REC-007",
      "org_chart_seat": "AI Systems Engineering",
      "role_title": "AI Systems Engineering Director",
      "organization": "Mojo",
      "owner_route": "Vik / MAPS ASPA and Engineering Director once hired",
      "priority": "High",
      "current_stage": "level_2_trainee",
      "stage_entered_at": "2026-06-24T16:54:30-06:00",
      "next_eligible_stage": "level_3_staff",
      "next_eligible_at": "2026-06-29T16:54:30-06:00",
      "status": "active",
      "level_1_packet": "C:\\Users\\scott\\Code\\mindshare\\roles\\recruiter\\level-4-work\\REC-007.md",
      "level_2_packet": "C:\\Users\\scott\\Code\\mindshare\\roles\\recruiter\\level-4-work\\REC-007-level2.md",
      "level_3_packet": null,
      "notes": "Named by Scott-directed Ana roster pass on 2026-06-24; remains an unactivated Level 2 Trainee packet. Seeded from completed Level 1 New Hire packet proof run; promotion timers governed by Ana Level 4 scoped autonomy.",
      "level_2_drive_packet": "G:\\My Drive\\Mindshare\\role\\recruiter\\level-4-work\\REC-007-level2.md",
      "person_name": "Theo Nakamura",
      "display_name": "Theo Nakamura / AI Systems Engineering Director"
    },
    {
      "id": "REC-008",
      "org_chart_seat": "Security Engineering",
      "role_title": "Security Engineering Director",
      "organization": "Mindshare / Mojo",
      "owner_route": "Technology Director once hired; coordinate with Reid and Tess",
      "priority": "High",
      "current_stage": "level_2_trainee",
      "stage_entered_at": "2026-06-24T16:54:30-06:00",
      "next_eligible_stage": "level_3_staff",
      "next_eligible_at": "2026-06-29T16:54:30-06:00",
      "status": "active",
      "level_1_packet": "C:\\Users\\scott\\Code\\mindshare\\roles\\recruiter\\level-4-work\\REC-008.md",
      "level_2_packet": "C:\\Users\\scott\\Code\\mindshare\\roles\\recruiter\\level-4-work\\REC-008-level2.md",
      "level_3_packet": null,
      "notes": "Named by Scott-directed Ana roster pass on 2026-06-24; remains an unactivated Level 2 Trainee packet. Seeded from completed Level 1 New Hire packet proof run; promotion timers governed by Ana Level 4 scoped autonomy.",
      "level_2_drive_packet": "G:\\My Drive\\Mindshare\\role\\recruiter\\level-4-work\\REC-008-level2.md",
      "person_name": "Harper Quinn",
      "display_name": "Harper Quinn / Security Engineering Director"
    },
    {
      "id": "REC-009",
      "org_chart_seat": "Chief Revenue Officer",
      "role_title": "Revenue Director",
      "organization": "Mindshare",
      "owner_route": "Rae / Chief Executive Officer",
      "priority": "High",
      "current_stage": "level_2_trainee",
      "stage_entered_at": "2026-06-24T16:54:30-06:00",
      "next_eligible_stage": "level_3_staff",
      "next_eligible_at": "2026-06-29T16:54:30-06:00",
      "status": "active",
      "level_1_packet": "C:\\Users\\scott\\Code\\mindshare\\roles\\recruiter\\level-4-work\\REC-009.md",
      "level_2_packet": "C:\\Users\\scott\\Code\\mindshare\\roles\\recruiter\\level-4-work\\REC-009-level2.md",
      "level_3_packet": null,
      "notes": "Named by Scott-directed Ana roster pass on 2026-06-24; remains an unactivated Level 2 Trainee packet. Seeded from completed Level 1 New Hire packet proof run; promotion timers governed by Ana Level 4 scoped autonomy.",
      "level_2_drive_packet": "G:\\My Drive\\Mindshare\\role\\recruiter\\level-4-work\\REC-009-level2.md",
      "person_name": "Sloane Mercer",
      "display_name": "Sloane Mercer / Revenue Director"
    },
    {
      "id": "REC-010",
      "org_chart_seat": "Chief Financial Officer",
      "role_title": "Finance Director",
      "organization": "Mindshare",
      "owner_route": "Rae / Chief Executive Officer",
      "priority": "Medium",
      "current_stage": "activated_operator",
      "stage_entered_at": "2026-06-22T12:39:43-06:00",
      "next_eligible_stage": null,
      "next_eligible_at": null,
      "status": "activated",
      "level_1_packet": "C:\\Users\\scott\\Code\\mindshare\\roles\\recruiter\\level-4-work\\REC-010.md",
      "level_2_packet": null,
      "level_3_packet": null,
      "notes": "Activated by Scott as Finn / Finance Director on 2026-06-23. Removed from timed Level 1/2/3 packet promotion queue; future changes require role-owner approval and finance authority gates.",
      "activated_role": "Finn",
      "activated_at": "2026-06-23T06:26:31-06:00",
      "activated_thread_id": "019ef46f-ac78-7932-bcb3-5426c5259a62",
      "activated_role_path": "C:\\Users\\scott\\Code\\mindshare\\roles\\finance-director\\role-agent.md"
    },
    {
      "id": "REC-011",
      "org_chart_seat": "Chief of Staff",
      "role_title": "Staff Operations Director",
      "organization": "Mindshare",
      "owner_route": "Rae / Chief Executive Officer",
      "priority": "High",
      "current_stage": "level_2_trainee",
      "stage_entered_at": "2026-06-24T16:54:30-06:00",
      "next_eligible_stage": "level_3_staff",
      "next_eligible_at": "2026-06-29T16:54:30-06:00",
      "status": "active",
      "level_1_packet": "C:\\Users\\scott\\Code\\mindshare\\roles\\recruiter\\level-4-work\\REC-011.md",
      "level_2_packet": "C:\\Users\\scott\\Code\\mindshare\\roles\\recruiter\\level-4-work\\REC-011-level2.md",
      "level_3_packet": null,
      "notes": "Named by Scott-directed Ana roster pass on 2026-06-24; remains an unactivated Level 2 Trainee packet. Seeded from completed Level 1 New Hire packet proof run; promotion timers governed by Ana Level 4 scoped autonomy.",
      "level_2_drive_packet": "G:\\My Drive\\Mindshare\\role\\recruiter\\level-4-work\\REC-011-level2.md",
      "person_name": "June Park",
      "display_name": "June Park / Staff Operations Director"
    },
    {
      "id": "REC-012",
      "org_chart_seat": "Executive Operations",
      "role_title": "Executive Operations Director",
      "organization": "Mindshare",
      "owner_route": "Operations Director once hired; interim Rae",
      "priority": "High",
      "current_stage": "level_2_trainee",
      "stage_entered_at": "2026-06-24T16:54:30-06:00",
      "next_eligible_stage": "level_3_staff",
      "next_eligible_at": "2026-06-29T16:54:30-06:00",
      "status": "active",
      "level_1_packet": "C:\\Users\\scott\\Code\\mindshare\\roles\\recruiter\\level-4-work\\REC-012.md",
      "level_2_packet": "C:\\Users\\scott\\Code\\mindshare\\roles\\recruiter\\level-4-work\\REC-012-level2.md",
      "level_3_packet": null,
      "notes": "Named by Scott-directed Ana roster pass on 2026-06-24; remains an unactivated Level 2 Trainee packet. Seeded from completed Level 1 New Hire packet proof run; promotion timers governed by Ana Level 4 scoped autonomy.",
      "level_2_drive_packet": "G:\\My Drive\\Mindshare\\role\\recruiter\\level-4-work\\REC-012-level2.md",
      "person_name": "Leon Archer",
      "display_name": "Leon Archer / Executive Operations Director"
    },
    {
      "id": "REC-013",
      "org_chart_seat": "Program Management Office",
      "role_title": "PMO Director",
      "organization": "Mindshare / Mojo",
      "owner_route": "Operations Director once hired; coordinate with Cal",
      "priority": "High",
      "current_stage": "level_2_trainee",
      "stage_entered_at": "2026-06-24T16:54:30-06:00",
      "next_eligible_stage": "level_3_staff",
      "next_eligible_at": "2026-06-29T16:54:30-06:00",
      "status": "active",
      "level_1_packet": "C:\\Users\\scott\\Code\\mindshare\\roles\\recruiter\\level-4-work\\REC-013.md",
      "level_2_packet": "C:\\Users\\scott\\Code\\mindshare\\roles\\recruiter\\level-4-work\\REC-013-level2.md",
      "level_3_packet": null,
      "notes": "Named by Scott-directed Ana roster pass on 2026-06-24; remains an unactivated Level 2 Trainee packet. Seeded from completed Level 1 New Hire packet proof run; promotion timers governed by Ana Level 4 scoped autonomy.",
      "level_2_drive_packet": "G:\\My Drive\\Mindshare\\role\\recruiter\\level-4-work\\REC-013-level2.md",
      "person_name": "Mira Patel",
      "display_name": "Mira Patel / PMO Director"
    },
    {
      "id": "REC-014",
      "org_chart_seat": "Product Management",
      "role_title": "Product Management Director",
      "organization": "Mindshare",
      "owner_route": "Product Director once hired",
      "priority": "High",
      "current_stage": "level_2_trainee",
      "stage_entered_at": "2026-06-24T16:54:30-06:00",
      "next_eligible_stage": "level_3_staff",
      "next_eligible_at": "2026-06-29T16:54:30-06:00",
      "status": "active",
      "level_1_packet": "C:\\Users\\scott\\Code\\mindshare\\roles\\recruiter\\level-4-work\\REC-014.md",
      "level_2_packet": "C:\\Users\\scott\\Code\\mindshare\\roles\\recruiter\\level-4-work\\REC-014-level2.md",
      "level_3_packet": null,
      "notes": "Named by Scott-directed Ana roster pass on 2026-06-24; remains an unactivated Level 2 Trainee packet. Seeded from completed Level 1 New Hire packet proof run; promotion timers governed by Ana Level 4 scoped autonomy.",
      "level_2_drive_packet": "G:\\My Drive\\Mindshare\\role\\recruiter\\level-4-work\\REC-014-level2.md",
      "person_name": "Gabe Rowan",
      "display_name": "Gabe Rowan / Product Management Director"
    },
    {
      "id": "REC-015",
      "org_chart_seat": "Product Operations",
      "role_title": "Product Operations Director",
      "organization": "Mindshare",
      "owner_route": "Product Director once hired",
      "priority": "Medium",
      "current_stage": "level_2_trainee",
      "stage_entered_at": "2026-06-24T16:54:30-06:00",
      "next_eligible_stage": "level_3_staff",
      "next_eligible_at": "2026-06-29T16:54:30-06:00",
      "status": "active",
      "level_1_packet": "C:\\Users\\scott\\Code\\mindshare\\roles\\recruiter\\level-4-work\\REC-015.md",
      "level_2_packet": "C:\\Users\\scott\\Code\\mindshare\\roles\\recruiter\\level-4-work\\REC-015-level2.md",
      "level_3_packet": null,
      "notes": "Named by Scott-directed Ana roster pass on 2026-06-24; remains an unactivated Level 2 Trainee packet. Seeded from completed Level 1 New Hire packet proof run; promotion timers governed by Ana Level 4 scoped autonomy.",
      "level_2_drive_packet": "G:\\My Drive\\Mindshare\\role\\recruiter\\level-4-work\\REC-015-level2.md",
      "person_name": "Elise Hart",
      "display_name": "Elise Hart / Product Operations Director"
    },
    {
      "id": "REC-016",
      "org_chart_seat": "Service Design",
      "role_title": "Service Design Director",
      "organization": "Mindshare",
      "owner_route": "Product Director once hired",
      "priority": "Medium",
      "current_stage": "level_2_trainee",
      "stage_entered_at": "2026-06-24T16:54:30-06:00",
      "next_eligible_stage": "level_3_staff",
      "next_eligible_at": "2026-06-29T16:54:30-06:00",
      "status": "active",
      "level_1_packet": "C:\\Users\\scott\\Code\\mindshare\\roles\\recruiter\\level-4-work\\REC-016.md",
      "level_2_packet": "C:\\Users\\scott\\Code\\mindshare\\roles\\recruiter\\level-4-work\\REC-016-level2.md",
      "level_3_packet": null,
      "notes": "Named by Scott-directed Ana roster pass on 2026-06-24; remains an unactivated Level 2 Trainee packet. Seeded from completed Level 1 New Hire packet proof run; promotion timers governed by Ana Level 4 scoped autonomy.",
      "level_2_drive_packet": "G:\\My Drive\\Mindshare\\role\\recruiter\\level-4-work\\REC-016-level2.md",
      "person_name": "Nora Voss",
      "display_name": "Nora Voss / Service Design Director"
    },
    {
      "id": "REC-017",
      "org_chart_seat": "Experience Design",
      "role_title": "Experience Design Director",
      "organization": "Mindshare",
      "owner_route": "Product Director once hired",
      "priority": "Medium",
      "current_stage": "level_2_trainee",
      "stage_entered_at": "2026-06-24T16:54:30-06:00",
      "next_eligible_stage": "level_3_staff",
      "next_eligible_at": "2026-06-29T16:54:30-06:00",
      "status": "active",
      "level_1_packet": "C:\\Users\\scott\\Code\\mindshare\\roles\\recruiter\\level-4-work\\REC-017.md",
      "level_2_packet": "C:\\Users\\scott\\Code\\mindshare\\roles\\recruiter\\level-4-work\\REC-017-level2.md",
      "level_3_packet": null,
      "notes": "Named by Scott-directed Ana roster pass on 2026-06-24; remains an unactivated Level 2 Trainee packet. Seeded from completed Level 1 New Hire packet proof run; promotion timers governed by Ana Level 4 scoped autonomy.",
      "level_2_drive_packet": "G:\\My Drive\\Mindshare\\role\\recruiter\\level-4-work\\REC-017-level2.md",
      "person_name": "Kai Bennett",
      "display_name": "Kai Bennett / Experience Design Director"
    },
    {
      "id": "REC-018",
      "org_chart_seat": "User Research",
      "role_title": "User Research Director",
      "organization": "Mindshare",
      "owner_route": "Product Director once hired",
      "priority": "Medium",
      "current_stage": "level_2_trainee",
      "stage_entered_at": "2026-06-24T16:54:30-06:00",
      "next_eligible_stage": "level_3_staff",
      "next_eligible_at": "2026-06-29T16:54:30-06:00",
      "status": "active",
      "level_1_packet": "C:\\Users\\scott\\Code\\mindshare\\roles\\recruiter\\level-4-work\\REC-018.md",
      "level_2_packet": "C:\\Users\\scott\\Code\\mindshare\\roles\\recruiter\\level-4-work\\REC-018-level2.md",
      "level_3_packet": null,
      "notes": "Named by Scott-directed Ana roster pass on 2026-06-24; remains an unactivated Level 2 Trainee packet. Seeded from completed Level 1 New Hire packet proof run; promotion timers governed by Ana Level 4 scoped autonomy.",
      "level_2_drive_packet": "G:\\My Drive\\Mindshare\\role\\recruiter\\level-4-work\\REC-018-level2.md",
      "person_name": "Amara Hayes",
      "display_name": "Amara Hayes / User Research Director"
    },
    {
      "id": "REC-019",
      "org_chart_seat": "Sales",
      "role_title": "Sales Director",
      "organization": "Mindshare",
      "owner_route": "Revenue Director once hired",
      "priority": "High",
      "current_stage": "level_2_trainee",
      "stage_entered_at": "2026-06-24T16:54:30-06:00",
      "next_eligible_stage": "level_3_staff",
      "next_eligible_at": "2026-06-29T16:54:30-06:00",
      "status": "active",
      "level_1_packet": "C:\\Users\\scott\\Code\\mindshare\\roles\\recruiter\\level-4-work\\REC-019.md",
      "level_2_packet": "C:\\Users\\scott\\Code\\mindshare\\roles\\recruiter\\level-4-work\\REC-019-level2.md",
      "level_3_packet": null,
      "notes": "Named by Scott-directed Ana roster pass on 2026-06-24; remains an unactivated Level 2 Trainee packet. Seeded from completed Level 1 New Hire packet proof run; promotion timers governed by Ana Level 4 scoped autonomy.",
      "level_2_drive_packet": "G:\\My Drive\\Mindshare\\role\\recruiter\\level-4-work\\REC-019-level2.md",
      "person_name": "Drew Collins",
      "display_name": "Drew Collins / Sales Director"
    },
    {
      "id": "REC-020",
      "org_chart_seat": "Partnerships",
      "role_title": "Partnerships Director",
      "organization": "Mindshare",
      "owner_route": "Revenue Director once hired",
      "priority": "Medium",
      "current_stage": "level_2_trainee",
      "stage_entered_at": "2026-06-24T16:54:30-06:00",
      "next_eligible_stage": "level_3_staff",
      "next_eligible_at": "2026-06-29T16:54:30-06:00",
      "status": "active",
      "level_1_packet": "C:\\Users\\scott\\Code\\mindshare\\roles\\recruiter\\level-4-work\\REC-020.md",
      "level_2_packet": "C:\\Users\\scott\\Code\\mindshare\\roles\\recruiter\\level-4-work\\REC-020-level2.md",
      "level_3_packet": null,
      "notes": "Named by Scott-directed Ana roster pass on 2026-06-24; remains an unactivated Level 2 Trainee packet. Seeded from completed Level 1 New Hire packet proof run; promotion timers governed by Ana Level 4 scoped autonomy.",
      "level_2_drive_packet": "G:\\My Drive\\Mindshare\\role\\recruiter\\level-4-work\\REC-020-level2.md",
      "person_name": "Celia Grant",
      "display_name": "Celia Grant / Partnerships Director"
    },
    {
      "id": "REC-021",
      "org_chart_seat": "Customer Success",
      "role_title": "Customer Success Director",
      "organization": "Mindshare / Watch / Mojo",
      "owner_route": "Revenue Director or Operations Director once hired",
      "priority": "High",
      "current_stage": "level_2_trainee",
      "stage_entered_at": "2026-06-24T16:54:30-06:00",
      "next_eligible_stage": "level_3_staff",
      "next_eligible_at": "2026-06-29T16:54:30-06:00",
      "status": "active",
      "level_1_packet": "C:\\Users\\scott\\Code\\mindshare\\roles\\recruiter\\level-4-work\\REC-021.md",
      "level_2_packet": "C:\\Users\\scott\\Code\\mindshare\\roles\\recruiter\\level-4-work\\REC-021-level2.md",
      "level_3_packet": null,
      "notes": "Named by Scott-directed Ana roster pass on 2026-06-24; remains an unactivated Level 2 Trainee packet. Seeded from completed Level 1 New Hire packet proof run; promotion timers governed by Ana Level 4 scoped autonomy.",
      "level_2_drive_packet": "G:\\My Drive\\Mindshare\\role\\recruiter\\level-4-work\\REC-021-level2.md",
      "person_name": "Jordan Hale",
      "display_name": "Jordan Hale / Customer Success Director"
    },
    {
      "id": "REC-022",
      "org_chart_seat": "Support",
      "role_title": "Support Director",
      "organization": "Mindshare",
      "owner_route": "Customer Success Director once hired",
      "priority": "Medium",
      "current_stage": "level_2_trainee",
      "stage_entered_at": "2026-06-24T16:54:30-06:00",
      "next_eligible_stage": "level_3_staff",
      "next_eligible_at": "2026-06-29T16:54:30-06:00",
      "status": "active",
      "level_1_packet": "C:\\Users\\scott\\Code\\mindshare\\roles\\recruiter\\level-4-work\\REC-022.md",
      "level_2_packet": "C:\\Users\\scott\\Code\\mindshare\\roles\\recruiter\\level-4-work\\REC-022-level2.md",
      "level_3_packet": null,
      "notes": "Named by Scott-directed Ana roster pass on 2026-06-24; remains an unactivated Level 2 Trainee packet. Seeded from completed Level 1 New Hire packet proof run; promotion timers governed by Ana Level 4 scoped autonomy.",
      "level_2_drive_packet": "G:\\My Drive\\Mindshare\\role\\recruiter\\level-4-work\\REC-022-level2.md",
      "person_name": "Samira Knox",
      "display_name": "Samira Knox / Support Director"
    },
    {
      "id": "REC-023",
      "org_chart_seat": "People Operations",
      "role_title": "People Operations Director",
      "organization": "Mindshare",
      "owner_route": "Operations Director once hired; coordinate with Cole and Ana",
      "priority": "Medium",
      "current_stage": "level_2_trainee",
      "stage_entered_at": "2026-06-24T16:54:30-06:00",
      "next_eligible_stage": "level_3_staff",
      "next_eligible_at": "2026-06-29T16:54:30-06:00",
      "status": "active",
      "level_1_packet": "C:\\Users\\scott\\Code\\mindshare\\roles\\recruiter\\level-4-work\\REC-023.md",
      "level_2_packet": "C:\\Users\\scott\\Code\\mindshare\\roles\\recruiter\\level-4-work\\REC-023-level2.md",
      "level_3_packet": null,
      "notes": "Named by Scott-directed Ana roster pass on 2026-06-24; remains an unactivated Level 2 Trainee packet. Seeded from completed Level 1 New Hire packet proof run; promotion timers governed by Ana Level 4 scoped autonomy.",
      "level_2_drive_packet": "G:\\My Drive\\Mindshare\\role\\recruiter\\level-4-work\\REC-023-level2.md",
      "person_name": "Mila Chen",
      "display_name": "Mila Chen / People Operations Director"
    },
    {
      "id": "REC-024",
      "org_chart_seat": "Legal",
      "role_title": "Legal Director",
      "organization": "Mindshare",
      "owner_route": "Finance Director or Operations Director once hired",
      "priority": "Medium",
      "current_stage": "level_2_trainee",
      "stage_entered_at": "2026-06-24T16:54:30-06:00",
      "next_eligible_stage": "level_3_staff",
      "next_eligible_at": "2026-06-29T16:54:30-06:00",
      "status": "active",
      "level_1_packet": "C:\\Users\\scott\\Code\\mindshare\\roles\\recruiter\\level-4-work\\REC-024.md",
      "level_2_packet": "C:\\Users\\scott\\Code\\mindshare\\roles\\recruiter\\level-4-work\\REC-024-level2.md",
      "level_3_packet": null,
      "notes": "Named by Scott-directed Ana roster pass on 2026-06-24; remains an unactivated Level 2 Trainee packet. Seeded from completed Level 1 New Hire packet proof run; promotion timers governed by Ana Level 4 scoped autonomy.",
      "level_2_drive_packet": "G:\\My Drive\\Mindshare\\role\\recruiter\\level-4-work\\REC-024-level2.md",
      "person_name": "Adrian Moss",
      "display_name": "Adrian Moss / Legal Director"
    },
    {
      "id": "REC-025",
      "org_chart_seat": "Compliance",
      "role_title": "Compliance Director",
      "organization": "Mindshare",
      "owner_route": "Legal Director once hired; coordinate with Reid and Tess",
      "priority": "Medium",
      "current_stage": "level_2_trainee",
      "stage_entered_at": "2026-06-24T16:54:30-06:00",
      "next_eligible_stage": "level_3_staff",
      "next_eligible_at": "2026-06-29T16:54:30-06:00",
      "status": "active",
      "level_1_packet": "C:\\Users\\scott\\Code\\mindshare\\roles\\recruiter\\level-4-work\\REC-025.md",
      "level_2_packet": "C:\\Users\\scott\\Code\\mindshare\\roles\\recruiter\\level-4-work\\REC-025-level2.md",
      "level_3_packet": null,
      "notes": "Named by Scott-directed Ana roster pass on 2026-06-24; remains an unactivated Level 2 Trainee packet. Seeded from completed Level 1 New Hire packet proof run; promotion timers governed by Ana Level 4 scoped autonomy.",
      "level_2_drive_packet": "G:\\My Drive\\Mindshare\\role\\recruiter\\level-4-work\\REC-025-level2.md",
      "person_name": "Isla Monroe",
      "display_name": "Isla Monroe / Compliance Director"
    },
    {
      "id": "REC-026",
      "org_chart_seat": "Vendor Management",
      "role_title": "Vendor Management Director",
      "organization": "Mindshare",
      "owner_route": "Finance Director or Operations Director once hired",
      "priority": "Medium",
      "current_stage": "level_2_trainee",
      "stage_entered_at": "2026-06-24T16:54:30-06:00",
      "next_eligible_stage": "level_3_staff",
      "next_eligible_at": "2026-06-29T16:54:30-06:00",
      "status": "active",
      "level_1_packet": "C:\\Users\\scott\\Code\\mindshare\\roles\\recruiter\\level-4-work\\REC-026.md",
      "level_2_packet": "C:\\Users\\scott\\Code\\mindshare\\roles\\recruiter\\level-4-work\\REC-026-level2.md",
      "level_3_packet": null,
      "notes": "Named by Scott-directed Ana roster pass on 2026-06-24; remains an unactivated Level 2 Trainee packet. Seeded from completed Level 1 New Hire packet proof run; promotion timers governed by Ana Level 4 scoped autonomy.",
      "level_2_drive_packet": "G:\\My Drive\\Mindshare\\role\\recruiter\\level-4-work\\REC-026-level2.md",
      "person_name": "Victor Lane",
      "display_name": "Victor Lane / Vendor Management Director"
    }
  ]
}
